__init__.py
machinegnostics/__init__.py
machinegnostics/magcal/__init__.py
machinegnostics/magcal/characteristics.py
machinegnostics/magcal/criteria_eval.py
machinegnostics/magcal/criterion.py
machinegnostics/magcal/data_conversion.py
machinegnostics/magcal/gcor.py
machinegnostics/magcal/layer_base.py
machinegnostics/magcal/layer_history_base.py
machinegnostics/magcal/layer_io_process_base.py
machinegnostics/magcal/layer_param_base.py
machinegnostics/magcal/mg_weights.py
machinegnostics/magcal/sample_characteristics.py
machinegnostics/magcal/scale_optimization.py
machinegnostics/magcal/scale_param.py
machinegnostics/magcal/gdf/__init__.py
machinegnostics/magcal/gdf/base_df.py
machinegnostics/magcal/gdf/base_distfunc.py
machinegnostics/magcal/gdf/base_egdf.py
machinegnostics/magcal/gdf/base_eldf.py
machinegnostics/magcal/gdf/base_qgdf.py
machinegnostics/magcal/gdf/base_qldf.py
machinegnostics/magcal/gdf/cluster_analysis.py
machinegnostics/magcal/gdf/data_cluster.py
machinegnostics/magcal/gdf/data_intervals.py
machinegnostics/magcal/gdf/data_membership.py
machinegnostics/magcal/gdf/der_egdf.py
machinegnostics/magcal/gdf/distfunc_engine.py
machinegnostics/magcal/gdf/egdf.py
machinegnostics/magcal/gdf/eldf.py
machinegnostics/magcal/gdf/eldf_intv.py
machinegnostics/magcal/gdf/eldf_ma.py
machinegnostics/magcal/gdf/homogeneity.py
machinegnostics/magcal/gdf/intv_engine.py
machinegnostics/magcal/gdf/marginal_intv_analysis.py
machinegnostics/magcal/gdf/qgdf.py
machinegnostics/magcal/gdf/qldf.py
machinegnostics/magcal/gdf/scedasticity.py
machinegnostics/magcal/gdf/wedf.py
machinegnostics/magcal/gdf/z0_estimator.py
machinegnostics/magcal/util/__init__.py
machinegnostics/magcal/util/dis_docstring.py
machinegnostics/magcal/util/logging.py
machinegnostics/magcal/util/min_max_float.py
machinegnostics/magnet/__init__.py
machinegnostics/metrics/__init__.py
machinegnostics/metrics/accu.py
machinegnostics/metrics/accuracy.py
machinegnostics/metrics/auto_correlation.py
machinegnostics-0.0.1.dist-info/licenses/LICENSE
machinegnostics-0.0.1.dist-info/METADATA
machinegnostics-0.0.1.dist-info/WHEEL
machinegnostics-0.0.1.dist-info/top_level.txt
machinegnostics-0.0.1.dist-info/RECORD
