Metadata-Version: 2.4
Name: machinegnostics
Version: 0.0.1
Summary: Machine Gnostics is an open-source initiative that seeks to redefine the mathematical underpinnings of machine learning. While most conventional ML libraries are grounded in probabilistic and statistical frameworks, Machine Gnostics explores alternative paradigms—drawing from Mathematical Gnostics, the non-statistical and deterministic approach. Laws of Nature, Encoded—For Everyone!
Author-email: Nirmal Parmar <info.machinegnostics@gmail.com>
Maintainer-email: Nirmal Parmar <info.machinegnostics@gmail.com>
License-Expression: GPL-3.0-only
Project-URL: Homepage, https://github.com/MachineGnostics
Project-URL: Issues, https://github.com/MachineGnostics/machinegnostics
Project-URL: Website, https://machinegnostics.info/
Keywords: machine learning,AI,data science,data analysis,deep learning,neural networks,ML,Machine Gnostics,Mathematical Gnostics
Classifier: Development Status :: 4 - Beta
Classifier: Intended Audience :: Science/Research
Classifier: Topic :: Scientific/Engineering :: Artificial Intelligence
Classifier: Programming Language :: Python :: 3
Classifier: Programming Language :: Python :: 3.9
Classifier: Programming Language :: Python :: 3.10
Classifier: Programming Language :: Python :: 3.11
Classifier: Operating System :: OS Independent
Requires-Python: >=3.9
License-File: LICENSE
Requires-Dist: fastapi
Requires-Dist: numpy
Requires-Dist: pandas
Requires-Dist: pydantic
Requires-Dist: scipy
Requires-Dist: SQLAlchemy
Dynamic: license-file
